weirwood_pyfinance/__init__.py
weirwood_pyfinance/finten.py
weirwood_pyfinance-0.1.1.dist-info/LICENSE
weirwood_pyfinance-0.1.1.dist-info/METADATA
weirwood_pyfinance-0.1.1.dist-info/WHEEL
weirwood_pyfinance-0.1.1.dist-info/entry_points.txt
weirwood_pyfinance-0.1.1.dist-info/top_level.txt
weirwood_pyfinance-0.1.1.dist-info/RECORD
